{"firstpage":1,"page":6,"nextpage":7,"prevpage":5,"totalpage":59,"data":[{"id":41,"keyword":"klx 150 2018","title":"Downloads klx 150 2018","slug":"Downloads-klx-150-2018","niche":"Kawasaki KLX","thumb":{"img":"https://zonamotor.net/wp-content/uploads/2018/12/IMG_20181118_160807-1.jpg","src":"https://zonamotor.net/2018/12/10/kawasaki-klx-150-bf-modif-supermoto-dengan-rangka-deltabox-bolt-on-ciamik-bro/","domain":"zonamotor.net"},"date":"2021-07-19"},{"id":42,"keyword":"klx bf se 2019","title":"Get klx bf se 2019","slug":"Get-klx-bf-se-2019","niche":"Kawasaki KLX","thumb":{"img":"https://i.ytimg.com/vi/XROPYX4E86g/maxresdefault.jpg","src":"https://www.youtube.com/watch?v=XROPYX4E86g","domain":"www.youtube.com"},"date":"2021-07-19"},{"id":43,"keyword":"kawasaki klx 150 bf se 2019","title":"Downloads kawasaki klx 150 bf se 2019","slug":"Downloads-kawasaki-klx-150-bf-se-2019","niche":"Kawasaki KLX","thumb":{"img":"https://cf.shopee.co.id/file/f902d554bdc23a83e2a004ad29544d76","src":"https://shopee.co.id/Striping-Sticker-Kawasaki-KLX-150-BF-2018-SE-Extreme-Hitam-i.93685346.2657758023","domain":"shopee.co.id"},"date":"2021-07-18"},{"id":44,"keyword":"kawasaki crf 150","title":"20++ kawasaki crf 150","slug":"20-kawasaki-crf-150","niche":"Kawasaki KLX","thumb":{"img":"https://imgcdn.zigwheels.ph/large/gallery/exterior/73/1172/honda-crf-150l-slant-front-view-full-image-853646.jpg","src":"https://www.zigwheels.ph/new-motorcycles/honda/crf150l/images","domain":"www.zigwheels.ph"},"date":"2021-07-14"},{"id":45,"keyword":"kawasaki klx 150cc","title":"20++ kawasaki klx 150cc","slug":"20-kawasaki-klx-150cc","niche":"Kawasaki KLX","thumb":{"img":"https://3.bp.blogspot.com/-Y6hfPM9JSlM/W4ON8rqFu9I/AAAAAAAAE34/ziODl9mxgJ4JHKAtxbtJ-Y_U1hzSGmLOgCLcBGAs/s1600/18581181_1555455074486689_8422615847402471424_n.jpg","src":"https://cupdate1.blogspot.com/2018/08/80-foto-modifikasi-motor-trail-kawasaki.html","domain":"cupdate1.blogspot.com"},"date":"2021-07-12"},{"id":46,"keyword":"jok klx","title":"Downloads jok klx","slug":"Downloads-jok-klx","niche":"Kawasaki KLX","thumb":{"img":"https://i1.wp.com/kawasaki-motoart.com/wp-content/uploads/2020/02/KLX-150G-Black1.jpg?fit=1067%2C801&ssl=1","src":"https://kawasaki-motoart.com/product/klx-150-g/","domain":"kawasaki-motoart.com"},"date":"2021-07-11"},{"id":47,"keyword":"klx 150r","title":"Downloads klx 150r","slug":"Downloads-klx-150r","niche":"Kawasaki KLX","thumb":{"img":"https://s.www.bermudayp.com/locations/47/photo/11/83/74/af/72011/photo_72011.jpg","src":"https://www.bermudayp.com/bizcast/view/584","domain":"www.bermudayp.com"},"date":"2021-07-10"},{"id":48,"keyword":"klx150bf for sale","title":"20++ klx150bf for sale","slug":"20-klx150bf-for-sale","niche":"Kawasaki KLX","thumb":{"img":"https://naikmotor.com/wp-content/uploads/2018/05/Kawasaki-KLX150BF-SE-Extreme-696x499.jpg","src":"https://www.naikmotor.com/95870/eh-ada-warna-baru-kawasaki-klx-150bf-se-extreme-di-jakarta-fair","domain":"www.naikmotor.com"},"date":"2021-07-10"}]}